{"inkVersion":21,"root":[[{"->":"main"},["done",{"#f":5,"#n":"g-0"}],null],"done",{"main":[["^Hey, salut toi !","\n","^Tu aimes les betraves ?","\n","ev","str","^Oui ! J'adore ça !","/str","/ev",{"*":".^.c-0","flg":20},"ev","str","^Non, c'est dégueulasse.","/str","/ev",{"*":".^.c-1","flg":20},"ev","str","^Ça s'écrit betteraves en fait ...","/str","/ev",{"*":".^.c-2","flg":20},{"c-0":["\n","^Ok.","\n",{"->":"conclusion"},{"#f":5}],"c-1":["\n","^Ok.","\n",{"->":"conclusion"},{"#f":5}],"c-2":["\n","^Comment tu fais pour lire se que je dis ?!","\n",{"->":"conclusion"},{"#f":5}]}],{"#f":1}],"conclusion":["^Casse-toi de là maintenant !","\n","end",{"#f":1}],"#f":1}],"listDefs":{}}